{
  "project_info": {
    "project_number": "583075617194",
    "project_id": "handson-ai",
    "storage_bucket": "handson-ai.appspot.com"
  },
  "client": [
    {
      "client_info": {
        "mobilesdk_app_id": "1:583075617194:android:bddffe19a64550212133d3",
        "android_client_info": {
          "package_name": "com.handson.handson"
        }
      },
      "oauth_client": [],
      "api_key": [
        {
          "current_key": "AIzaSyBGHYplVsWkvZb8O5RVe7pUqywEeqb51xw"
        }
      ],
      "services": {
        "appinvite_service": {
          "other_platform_oauth_client": []
        }
      }
    }
  ],
  "configuration_version": "1"
}